{
  "objectInfo" : {
    "id" : "8SWdXoHhXasieHg9wbQH8y",
    "name" : "MCT_inlineActionDepen",
    "type" : "MTT",
    "metadata" : {
      "modelVersion" : {
        "major" : 0,
        "minor" : 0
      },
      "repoInfo" : {
        "repoHandle" : "0100080Z000000000004"
      },
      "contextAttributes" : [ {
        "name" : "id",
        "value" : "@1"
      } ],
      "additionalInfo" : {
        "description" : "",
        "contentType" : "JSON",
        "documentState" : "VALID"
      }
    }
  },
  "dataFileExtension" : "zip",
  "objectRefs" : [ {
    "id" : "hRpPKHPv9YQdu4qHseuZO7",
    "name" : "TMS33RH64001",
    "type" : "AgentGroup",
    "metadata" : {
      "modelVersion" : {
        "major" : 0,
        "minor" : 0
      },
      "repoInfo" : {
        "repoHandle" : "01000825000000000002"
      },
      "contextAttributes" : null,
      "additionalInfo" : {
        "description" : null,
        "contentType" : "JSON",
        "documentState" : "VALID"
      }
    },
    "path" : "/SYS"
  }, {
    "id" : "8aJaZKwhm82dpTv8UjeDaS",
    "name" : "cmd_inlineActionDepen",
    "type" : "DTEMPLATE",
    "metadata" : {
      "modelVersion" : {
        "major" : 0,
        "minor" : 0
      },
      "repoInfo" : {
        "repoHandle" : "01000817000000000003"
      },
      "contextAttributes" : null,
      "additionalInfo" : {
        "description" : "Multiple Lookup Condition",
        "contentType" : "JSON",
        "documentState" : "VALID"
      }
    },
    "path" : "/Explore/Default"
  }, {
    "id" : "0qitEwsMuaRl2uQxNci9SF",
    "name" : "FF",
    "type" : "Connection",
    "metadata" : {
      "modelVersion" : {
        "major" : 0,
        "minor" : 0
      },
      "repoInfo" : {
        "repoHandle" : "0100080B000000000003"
      },
      "contextAttributes" : null,
      "additionalInfo" : {
        "description" : "test desc",
        "contentType" : "JSON",
        "documentState" : "COMPLETE"
      }
    },
    "path" : "/SYS"
  } ]
}